dejunk/__init__.py
dejunk/cli.py
dejunk/dejunk.py
dejunk-0.1.1.dist-info/AUTHORS.rst
dejunk-0.1.1.dist-info/LICENSE
dejunk-0.1.1.dist-info/METADATA
dejunk-0.1.1.dist-info/WHEEL
dejunk-0.1.1.dist-info/entry_points.txt
dejunk-0.1.1.dist-info/top_level.txt
dejunk-0.1.1.dist-info/RECORD
