Metadata-Version: 2.1
Name: dejunk
Version: 0.1.1
Summary: block any junk and improve your browsing experience
Home-page: https://github.com/nidhaloff/dejunk
Author: Nidhal Baccouri
Author-email: nidhalbacc@gmail.com
License: GNU General Public License v3
Keywords: dejunk
Platform: UNKNOWN
Classifier: Development Status :: 4 - Beta
Classifier: Intended Audience :: Developers
Classifier: License :: OSI Approved :: GNU General Public License v3 (GPLv3)
Classifier: Natural Language :: English
Classifier: Programming Language :: Python :: 3
Classifier: Programming Language :: Python :: 3.5
Classifier: Programming Language :: Python :: 3.6
Classifier: Programming Language :: Python :: 3.7
Classifier: Programming Language :: Python :: 3.8
Requires-Python: >=3.5
